README.md
setup.py
glosbevocabscraper/__init__.py
glosbevocabscraper/codes.array
glosbevocabscraper/main.py
glosbevocabscraper.egg-info/PKG-INFO
glosbevocabscraper.egg-info/SOURCES.txt
glosbevocabscraper.egg-info/dependency_links.txt
glosbevocabscraper.egg-info/entry_points.txt
glosbevocabscraper.egg-info/requires.txt
glosbevocabscraper.egg-info/top_level.txt
venv/__init__.py
venv/bin/__init__.py
venv/bin/activate_this.py
venv/bin/rst2html.py
venv/bin/rst2html4.py
venv/bin/rst2html5.py
venv/bin/rst2latex.py
venv/bin/rst2man.py
venv/bin/rst2odt.py
venv/bin/rst2odt_prepstyles.py
venv/bin/rst2pseudoxml.py
venv/bin/rst2s5.py
venv/bin/rst2xetex.py
venv/bin/rst2xml.py
venv/bin/rstpep2html.py
venv/lib/__init__.py