Metadata-Version: 2.1
Name: glosbevocabscraper
Version: 1.0.0
Summary: Scrapes translations, example sentences and audio from glosbe
Home-page: https://github.com/dotdioscorea/glosbevocabscraper
Author: dotdioscorea
Author-email: git@awr.sh
License: MIT
Platform: UNKNOWN
Classifier: Development Status :: 4 - Beta
Classifier: Intended Audience :: Education
Classifier: License :: OSI Approved :: MIT No Attribution License (MIT-0)
Classifier: Operating System :: OS Independent
Classifier: Programming Language :: Python :: 2
Classifier: Programming Language :: Python :: 2.7
Classifier: Programming Language :: Python :: 3
Classifier: Programming Language :: Python :: 3.4
Classifier: Programming Language :: Python :: 3.5
